external/shared/fixtures/env_helper.py
external/shared/fixtures/sys_path_helper.py
plugin/plugin_manager.py
monad_maker_fm-0.0.4.dist-info/LICENSE
monad_maker_fm-0.0.4.dist-info/METADATA
monad_maker_fm-0.0.4.dist-info/WHEEL
monad_maker_fm-0.0.4.dist-info/top_level.txt
monad_maker_fm-0.0.4.dist-info/RECORD
